{
    "問題": "AがBとの間で、A所有の甲土地につき建物所有目的で期間を50年とする賃貸借契約（以下この問において「本件契約」という。）を締結する場合に関する次の記述のうち、借地借家法の規定及び判例によれば、正しいものはどれか。",
    "問題年度": "r5",
    "問題番号": "11",
    "問題タイプ": "正しいものを選ぶ",
    "選択肢": [
        "本件契約に、当初の10年間は地代を減額しない旨の特約を定めた場合、その期間内は、BはAに対して地代の減額請求をすることはできない。",
        "本件契約が甲土地上で専ら賃貸アパート事業用の建物を所有する目的である場合、契約の更新や建物の築造による存続期間の延長がない旨を定めるためには、公正証書で合意しなければならない。",
        "本件契約に建物買取請求権を排除する旨の特約が定められていない場合、本件契約が終了したときは、その終了事由のいかんにかかわらず、BはAに対してBが甲土地上に所有している建物を時価で買い取るべきことを請求することができる。",
        "本件契約がBの居住のための建物を所有する目的であり契約の更新がない旨を定めていない契約であって、期間満了する場合において甲土地上に建物があり、Bが契約の更新を請求したとしても、Aが遅滞なく異議を述べ、その異議に更新を拒絶する正当な事由があると認められる場合は、本件契約は更新されない。"
    ],
    "正解番号": 4,
    "解説": [
        "1: 誤り。借地借家法第11条により、特約があってもBは地代の減額請求をすることができる。",
        "2:\n 誤り。\n公正証書が必須ではなく、契約書で十分に契約の更新拒絶を排除することができる。\nＢは、甲土地上に「専ら賃貸アパート事業用の建物を所有」する目的を持っています。つまり、「居住用建物」を経営しようとしているわけです。\nこの場合、事業用定期借地権を設定することはできません。利用可能なのは、最低50年以上の期間を確保した一般定期借地権に限られます。\nそして、一般定期借地権を設定する場合、書面で契約する必要があります（借地借家法22条１項。\n電磁的記録による契約も、書面による契約とみなされます）。\nこの契約は「書面」によればいいのであって、「公正証書」であることまでは要求されていません。\nなぜ事業用にならないか\n事業用定期借地権は、非居住用の事業のための土地利用（商業施設やオフィス、工場など）が対象です。\n賃貸アパートは「居住用建物」に該当し、事業用定期借地権の対象外となります。\n商業用や工業用の土地利用に関して、事業用定期借地権が導入され、より厳しい規制や条件が課されている理由は、土地の利用目的や経済的な影響が大きく異なるためです。",
        "3: 誤り。借地借家法第13条により、建物買取請求権は契約が期間満了で終了する場合にのみ発生し、終了事由によっては認められない。",
        "4: 正しい。借地借家法第5条第1項および第6条により、Aが正当事由をもって異議を述べた場合、契約は更新されない。"
    ],
    "カテゴリ": "借地借家法",
    "キーワード": [
        "地代",
        "契約更新",
        "建物買取請求権",
        "正当事由"
    ],
    "理解度": 0.0,
    "付帯情報": "借地借家法における契約更新や地代に関する条文を理解することが重要です。",
    "画像リンク": "/mnt/data/image.png"
}